rapidgeo-0.2.1.dist-info/METADATA
rapidgeo-0.2.1.dist-info/WHEEL
rapidgeo/__init__.py
rapidgeo/_rapidgeo.cpython-313-darwin.so
rapidgeo/distance/__init__.py
rapidgeo/distance/batch.py
rapidgeo/distance/euclid.py
rapidgeo/distance/geo.py
rapidgeo/formats/__init__.py
rapidgeo/polyline/__init__.py
rapidgeo/similarity/__init__.py
rapidgeo/similarity/frechet.py
rapidgeo/similarity/hausdorff.py
rapidgeo/simplify/__init__.py
rapidgeo/simplify/batch.py
rapidgeo-0.2.1.dist-info/RECORD
