Metadata-Version: 2.4
Name: rapidgeo
Version: 0.2.1
Classifier: Development Status :: 4 - Beta
Classifier: Intended Audience :: Developers
Classifier: License :: OSI Approved :: MIT License
Classifier: License :: OSI Approved :: Apache Software License
Classifier: Programming Language :: Python :: 3
Classifier: Programming Language :: Python :: 3.8
Classifier: Programming Language :: Python :: 3.9
Classifier: Programming Language :: Python :: 3.10
Classifier: Programming Language :: Python :: 3.11
Classifier: Programming Language :: Python :: 3.12
Classifier: Programming Language :: Rust
Classifier: Topic :: Scientific/Engineering :: GIS
Classifier: Topic :: Software Development :: Libraries :: Python Modules
Requires-Dist: numpy>=1.19.0 ; extra == 'numpy'
Provides-Extra: numpy
Summary: Fast geographic and planar distance calculations with Python bindings
Keywords: distance,geodesic,haversine,vincenty,geometry,gis
Home-Page: https://github.com/gaker/rapidgeo
Author: gaker
License: MIT OR Apache-2.0
Requires-Python: >=3.8
Project-URL: Homepage, https://github.com/gaker/rapidgeo
Project-URL: Repository, https://github.com/gaker/rapidgeo
Project-URL: Documentation, https://rapidgeo.readthedocs.io/
Project-URL: Issues, https://github.com/gaker/rapidgeo/issues
